davidjaramillo/__init__.py
davidjaramillo/matemáticas.py
davidjaramillo-0.1.0.dist-info/METADATA
davidjaramillo-0.1.0.dist-info/WHEEL
davidjaramillo-0.1.0.dist-info/RECORD
