Metadata-Version: 2.1
Name: davidjaramillo
Version: 0.1.0
Summary: Paquete de programación
Author: David Jaramillo
Author-email: dejaramillo28@utpl.edu.ec
Requires-Python: >=3.10.0,<3.12
Classifier: Programming Language :: Python :: 3
Classifier: Programming Language :: Python :: 3.10
Classifier: Programming Language :: Python :: 3.11
